openqasm/openqasm.py
openqasm-0.0.1.dist-info/METADATA
openqasm-0.0.1.dist-info/RECORD
openqasm-0.0.1.dist-info/WHEEL
openqasm-0.0.1.dist-info/top_level.txt
