Metadata-Version: 2.1
Name: openqasm
Version: 0.0.1
Summary: Parser for OPENQASM
Home-page: https://github.com/qevedo/openqasm
Author: Alex
Author-email: alxmorais8@msn.com
License: Apache License
